{
  "titlecard": "Enigma: Tutorials",
  "titlestyle": "background: linear-gradient(to bottom, rgba(252,234,187,1) 0%, rgba(252,205,77,1) 50%, rgba(248,181,0,1) 51%, rgba(251,223,147,1) 100%); -webkit-background-clip: text; -webkit-text-fill-color: transparent;",
  "results": [
    {
      "title": "Unload",
      "des": "Unloads the current item",
      "utility": true,
      "func": true,
      "run": "unload();"
    },{
      "title": "Assembling a Repo",
      "des": "You can check the JSON files you know, it's not hard.",
      "learn": true,
      "pro": true,
      "run": "change('./more/assemble-repo.html');"
    },{
      "title": "Assembling a Package",
      "des": "You can still just look at JSON...",
      "pro": true,
      "learn": true,
      "run": "change('./more/assemble-package.html');"
    },{
      "title": "Private Badge Handling",
      "des": "How the \"Private\" is handled with some methods",
      "pro": true,
      "learn": true,
      "run": "change('./more/private-tag.html');"
    }
  ]
}
